{
  "properties": [
    {
      "name": "lilys.ai.api.url",
      "type": "java.lang.String",
      "description": "Base URL for the Lilys AI API service."
    },
    {
      "name": "lilys.ai.api.key",
      "type": "java.lang.String",
      "description": "Authentication API key for the Lilys AI service."
    },
    {
      "name": "google.custom.search.api.key",
      "type": "java.lang.String",
      "description": "Description for google.custom.search.api.key."
    },
    {
      "name": "google.custom.search.engine.id",
      "type": "java.lang.String",
      "description": "Description for google.custom.search.engine.id."
    },
    {
      "name": "embedding.api.url",
      "type": "java.lang.String",
      "description": "Description for embedding.api.url."
    },
    {
      "name": "fcm.credentials.path",
      "type": "java.lang.String",
      "description": "Description for fcm.credentials.path."
    },
    {
      "name": "youtube.api.key",
      "type": "java.lang.String",
      "description": "Description for youtube.api.key."
    }
  ]
}